pycompanydata/__init__.py
pycompanydata/clients/__init__.py
pycompanydata/clients/accounting_client.py
pycompanydata/clients/base_client.py
pycompanydata/clients/platform_client.py
pycompanydata/data_types/__init__.py
pycompanydata/data_types/accounting/__init__.py
pycompanydata/data_types/accounting/account_transactions.py
pycompanydata/data_types/accounting/accounts.py
pycompanydata/data_types/accounting/bills.py
pycompanydata/data_types/accounting/invoices.py
pycompanydata/data_types/accounting/payments.py
pycompanydata/data_types/accounting/suppliers.py
pycompanydata/data_types/accounting/typed_refs.py
pycompanydata/data_types/pagination.py
pycompanydata/data_types/platform/__init__.py
pycompanydata/data_types/platform/company.py
pycompanydata/data_types/platform/connections.py
pycompanydata/data_types/platform/datasetmetadata.py
pycompanydata/data_types/platform/datastatus.py
pycompanydata/data_types/platform/exceptions.py
pycompanydata/data_types/platform/syncsettings.py
pycompanydata/handlers/__init__.py
pycompanydata/handlers/accounting/__init__.py
pycompanydata/handlers/accounting/account_transaction_handler.py
pycompanydata/handlers/accounting/accounts_handler.py
pycompanydata/handlers/accounting/bills_handler.py
pycompanydata/handlers/accounting/invoices_handler.py
pycompanydata/handlers/accounting/payments_handler.py
pycompanydata/handlers/accounting/suppliers_handler.py
pycompanydata/handlers/base.py
pycompanydata/handlers/platform/__init__.py
pycompanydata/handlers/platform/companyhandler.py
pycompanydata/handlers/platform/connectionhandler.py
pycompanydata/handlers/platform/datasetmetadatahandler.py
pycompanydata/handlers/platform/datastatushandler.py
pycompanydata/handlers/platform/syncsettingshandler.py
pycompanydata/rest_adapter.py
pycompanydata-0.1.3.dist-info/LICENSE.md
pycompanydata-0.1.3.dist-info/WHEEL
pycompanydata-0.1.3.dist-info/METADATA
pycompanydata-0.1.3.dist-info/RECORD
