Metadata-Version: 2.1
Name: pycompanydata
Version: 0.1.3
Summary: A Python client library for interacting with the Codat API
Author: Peter Simpson
Author-email: peter_joseph_simpson@hotmail.com
Requires-Python: >=3.8,<4.0
Classifier: Programming Language :: Python :: 3
Classifier: Programming Language :: Python :: 3.8
Classifier: Programming Language :: Python :: 3.9
Classifier: Programming Language :: Python :: 3.10
Requires-Dist: Sphinx (>=5.1.1,<6.0.0)
Requires-Dist: pydantic (>=1.9.2,<2.0.0)
Requires-Dist: requests (>=2.28.1,<3.0.0)
Requires-Dist: sphinx-rtd-theme (>=1.0.0,<2.0.0)
Requires-Dist: types-toml (>=0.10.8.5,<0.11.0.0)
